decentralise/__init__.py
decentralise/parse_stan.py
decentralise-0.0.1.dist-info/LICENSE
decentralise-0.0.1.dist-info/METADATA
decentralise-0.0.1.dist-info/WHEEL
decentralise-0.0.1.dist-info/entry_points.txt
decentralise-0.0.1.dist-info/top_level.txt
decentralise-0.0.1.dist-info/RECORD
