Metadata-Version: 2.1
Name: decentralise
Version: 0.0.1
Summary: Make normally distributed parameters non-centered in Stan programs.
Home-page: https://github.com/anguswilliams91/decentralise
Author: Angus Williams
Author-email: anguswilliams91@gmail.com
License: MIT
Download-URL: https://github.com/anguswilliams91/decentralise/archive/master.zip
Platform: UNKNOWN
Requires-Python: >=3.6
